flaskoidc/__init__.py
flaskoidc/config.py
flaskoidc/models.py
secoda_flaskoidc-1.0.10.dist-info/LICENSE
secoda_flaskoidc-1.0.10.dist-info/METADATA
secoda_flaskoidc-1.0.10.dist-info/WHEEL
secoda_flaskoidc-1.0.10.dist-info/top_level.txt
secoda_flaskoidc-1.0.10.dist-info/RECORD
