Metadata-Version: 2.1
Name: secoda-flaskoidc
Version: 1.0.10
Summary: Flask wrapper with pre-configured OAuth2 and OIDC support
Home-page: https://github.com/verdan/flaskoidc.git
Author: Andrew McEwen
Author-email: andrew@secoda.co
License: UNKNOWN
Platform: UNKNOWN
Requires-Python: >=3.6
License-File: LICENSE
Requires-Dist: Flask (>=1.0.2)
Requires-Dist: Authlib (>=0.15.4)
Requires-Dist: requests (>=2.25.1)
Requires-Dist: Flask-SQLAlchemy (>=2.5.1)
